flickr_api/__init__.py
flickr_api/_version.py
flickr_api/api.py
flickr_api/auth.py
flickr_api/cache.py
flickr_api/flickrerrors.py
flickr_api/keys.py
flickr_api/method_call.py
flickr_api/methods.py
flickr_api/methods.py.tmpl
flickr_api/objects.py
flickr_api/py.typed
flickr_api/reflection.py
flickr_api/tools.py
flickr_api/upload.py
flickr_api/utils.py
flickr_api-0.8.0.dist-info/METADATA
flickr_api-0.8.0.dist-info/WHEEL
flickr_api-0.8.0.dist-info/licenses/LICENSE.txt
flickr_api-0.8.0.dist-info/RECORD
