Metadata-Version: 2.4
Name: flickr_api
Version: 0.8.0
Summary: Python wrapper for the Flickr API
Project-URL: Homepage, https://github.com/alexis-mignon/python-flickr-api
Project-URL: Repository, https://github.com/alexis-mignon/python-flickr-api
Author-email: Alexis Mignon <alexis.mignon@gmail.com>
License-Expression: BSD-3-Clause
License-File: LICENSE.txt
Classifier: Intended Audience :: Developers
Classifier: License :: OSI Approved :: BSD License
Classifier: Programming Language :: Python :: 3
Classifier: Programming Language :: Python :: 3.10
Classifier: Programming Language :: Python :: 3.11
Classifier: Programming Language :: Python :: 3.12
Classifier: Programming Language :: Python :: 3.13
Requires-Python: >=3.10
Requires-Dist: requests
Requires-Dist: requests-oauthlib
